alu.v
//8 bit alu

module alu(a , b , select , out ,carry , flag);

input [7:0] a ,b ;
input [3:0] select;

output reg[7:0] out;
output carry;
output reg flag ;

wire [8:0]temp;

assign temp = {1'b0 , a} + {1'b0 , b};
assign carry = (select == 4'b0000) ? temp[8] : 1'b0;

always @(*)

begin
case(select)
        4'b0000: out = temp[7:0];                 // Addition
        4'b0001: out = a - b;                     // Subtraction
        4'b0010: out = a & b;                     // AND
        4'b0011: out = a | b;                     // OR
        4'b0100: out = a ^ b;                     // XOR
        4'b0101: out = ~a;                        // NOT A
        4'b0110: out = a << 1;                    // Logical Left Shift
        4'b0111: out = a >> 1;                    // Logical Right Shift
        4'b1000: out = (a < b) ? 8'b00000001 : 8'b00000000;  // check if less than
        default: out = 8'b00000000;               // Default case

endcase
        if(out == 8'b00000000)
         
          flag= 1'b1;
        else 
        flag = 1'b0; 


end

endmodule

testbench.v
`timescale 1ns / 1ps

module testbench;

reg [7:0] a,b;
reg[3:0] select;

wire[7:0] out;
wire carry;
wire flag;
integer i;

alu al(.a(a),.b(b),.select(select),.out(out),.carry(carry) ,.flag(flag));


initial
begin
a = 8'd10; 
b = 8'd5;
select = 4'b0000;


for(i =0 ; i < 9; i = i+1)
begin
select = i;
#10;
end
#20 $finish;

end


initial begin
$dumpfile("alu.vcd");
$dumpvars(0, testbench);

 $monitor($time," | select = %b | a = %d | b = %d | out = %d | carry = %b | flag = %b ", select, a, b, out, carry, flag);

end


endmodule

alu.vcd
$date
	Mon Jun 23 23:34:22 2025
$end
$version
	Icarus Verilog
$end
$timescale
	1ps
$end
$scope module testbench $end
$var wire 8 ! out [7:0] $end
$var wire 1 " flag $end
$var wire 1 # carry $end
$var reg 8 $ a [7:0] $end
$var reg 8 % b [7:0] $end
$var reg 4 & select [3:0] $end
$var integer 32 ' i [31:0] $end
$scope module al $end
$var wire 8 ( a [7:0] $end
$var wire 8 ) b [7:0] $end
$var wire 4 * select [3:0] $end
$var wire 9 + temp [8:0] $end
$var wire 1 # carry $end
$var reg 1 " flag $end
$var reg 8 , out [7:0] $end
$upscope $end
$upscope $end
$enddefinitions $end
$comment Show the parameter values. $end
$dumpall
$end
#0
$dumpvars
b1111 ,
b1111 +
b0 *
b101 )
b1010 (
b0 '
b0 &
b101 %
b1010 $
0#
0"
b1111 !
$end
#10000
b101 !
b101 ,
b1 &
b1 *
b1 '
#20000
1"
b0 !
b0 ,
b10 &
b10 *
b10 '
#30000
0"
b1111 !
b1111 ,
b11 &
b11 *
b11 '
#40000
b100 &
b100 *
b100 '
#50000
b11110101 !
b11110101 ,
b101 &
b101 *
b101 '
#60000
b10100 !
b10100 ,
b110 &
b110 *
b110 '
#70000
b101 !
b101 ,
b111 &
b111 *
b111 '
#80000
1"
b0 !
b0 ,
b1000 &
b1000 *
b1000 '
#90000
b1001 '
